{
	"info": {
		"_postman_id": "0d647807-e569-4c4a-a5e6-93e1a0bf0846",
		"name": "persons",
		"schema": "https://schema.getpostman.com/json/collection/v2.1.0/collection.json",
		"_exporter_id": "12635879"
	},
	"item": [
		{
			"name": "add person",
			"request": {
				"auth": {
					"type": "basic",
					"basic": [
						{
							"key": "password",
							"value": "admin",
							"type": "string"
						},
						{
							"key": "username",
							"value": "admin",
							"type": "string"
						}
					]
				},
				"method": "POST",
				"header": [],
				"body": {
					"mode": "raw",
					"raw": "{\n    \"name\": \"ahmmmmm\"\n}",
					"options": {
						"raw": {
							"language": "json"
						}
					}
				},
				"url": {
					"raw": "http://localhost:8081/persons",
					"protocol": "http",
					"host": [
						"localhost"
					],
					"port": "8081",
					"path": [
						"persons"
					]
				}
			},
			"response": []
		},
		{
			"name": "get all person",
			"protocolProfileBehavior": {
				"disableBodyPruning": true
			},
			"request": {
				"auth": {
					"type": "basic",
					"basic": [
						{
							"key": "password",
							"value": "admin",
							"type": "string"
						},
						{
							"key": "username",
							"value": "admin",
							"type": "string"
						}
					]
				},
				"method": "GET",
				"header": [],
				"body": {
					"mode": "raw",
					"raw": "{\n    \"name\": \"ahmmmmm\"\n}",
					"options": {
						"raw": {
							"language": "json"
						}
					}
				},
				"url": {
					"raw": "http://localhost:8081/persons/c5a4c8a4-ad2b-431d-ae55-485b4312da87",
					"protocol": "http",
					"host": [
						"localhost"
					],
					"port": "8081",
					"path": [
						"persons",
						"c5a4c8a4-ad2b-431d-ae55-485b4312da87"
					]
				}
			},
			"response": []
		},
		{
			"name": "get person detail",
			"protocolProfileBehavior": {
				"disableBodyPruning": true
			},
			"request": {
				"auth": {
					"type": "basic",
					"basic": [
						{
							"key": "password",
							"value": "admin",
							"type": "string"
						},
						{
							"key": "username",
							"value": "admin",
							"type": "string"
						}
					]
				},
				"method": "GET",
				"header": [],
				"body": {
					"mode": "raw",
					"raw": "{\n    \"name\": \"ahmmmmm\"\n}",
					"options": {
						"raw": {
							"language": "json"
						}
					}
				},
				"url": {
					"raw": "http://localhost:8081/persons/c5a4c8a4-ad2b-431d-ae55-485b4312da87",
					"protocol": "http",
					"host": [
						"localhost"
					],
					"port": "8081",
					"path": [
						"persons",
						"c5a4c8a4-ad2b-431d-ae55-485b4312da87"
					]
				}
			},
			"response": []
		},
		{
			"name": "delete person",
			"request": {
				"auth": {
					"type": "basic",
					"basic": [
						{
							"key": "password",
							"value": "admin",
							"type": "string"
						},
						{
							"key": "username",
							"value": "admin",
							"type": "string"
						}
					]
				},
				"method": "DELETE",
				"header": [],
				"body": {
					"mode": "raw",
					"raw": "{\n    \"name\": \"ahmmmmm\"\n}",
					"options": {
						"raw": {
							"language": "json"
						}
					}
				},
				"url": {
					"raw": "http://localhost:8081/persons/dcdc74a4-81bd-4528-9be4-e2eb5c2683ac",
					"protocol": "http",
					"host": [
						"localhost"
					],
					"port": "8081",
					"path": [
						"persons",
						"dcdc74a4-81bd-4528-9be4-e2eb5c2683ac"
					]
				}
			},
			"response": []
		},
		{
			"name": "update person detail",
			"protocolProfileBehavior": {
				"disableBodyPruning": true
			},
			"request": {
				"auth": {
					"type": "basic",
					"basic": [
						{
							"key": "password",
							"value": "admin",
							"type": "string"
						},
						{
							"key": "username",
							"value": "admin",
							"type": "string"
						}
					]
				},
				"method": "GET",
				"header": [],
				"body": {
					"mode": "raw",
					"raw": "{\n    \"name\": \"ahmmmmm\"\n}",
					"options": {
						"raw": {
							"language": "json"
						}
					}
				},
				"url": {
					"raw": "http://localhost:8081/persons/c5a4c8a4-ad2b-431d-ae55-485b4312da87",
					"protocol": "http",
					"host": [
						"localhost"
					],
					"port": "8081",
					"path": [
						"persons",
						"c5a4c8a4-ad2b-431d-ae55-485b4312da87"
					]
				}
			},
			"response": []
		}
	]
}